SoMeWeTa-1.8.1.data/scripts/somewe-tagger
someweta/__init__.py
someweta/averaged_structured_perceptron.py
someweta/cli.py
someweta/tagger.py
someweta/utils.py
someweta/version.py
SoMeWeTa-1.8.1.dist-info/LICENSE.txt
SoMeWeTa-1.8.1.dist-info/METADATA
SoMeWeTa-1.8.1.dist-info/WHEEL
SoMeWeTa-1.8.1.dist-info/top_level.txt
SoMeWeTa-1.8.1.dist-info/RECORD
