Metadata-Version: 2.1
Name: SoMeWeTa
Version: 1.8.1
Summary: A part-of-speech tagger with support for domain adaptation and external resources.
Home-page: https://github.com/tsproisl/SoMeWeTa
Author: Thomas Proisl
Author-email: thomas.proisl@fau.de
License: GNU General Public License v3 or later (GPLv3+)
Download-URL: https://github.com/tsproisl/SoMeWeTa/archive/v1.8.1.tar.gz
Platform: UNKNOWN
Classifier: Development Status :: 4 - Beta
Classifier: Environment :: Console
Classifier: Intended Audience :: Developers
Classifier: Intended Audience :: Science/Research
Classifier: License :: OSI Approved :: GNU General Public License v3 or later (GPLv3+)
Classifier: Natural Language :: English
Classifier: Natural Language :: French
Classifier: Natural Language :: German
Classifier: Operating System :: OS Independent
Classifier: Programming Language :: Python :: 3
Classifier: Topic :: Text Processing :: Linguistic
Requires-Python: >=3.4
Requires-Dist: numpy
Requires-Dist: regex (>=2019.02.18)
